pyramid/__init__.py
pyramid/_config.py
pyramid/setup.py
pyramid/__check_build/__init__.py
pyramid/__check_build/_check_build.cp35-win_amd64.pyd
pyramid/__check_build/setup.py
pyramid/__check_build/tests/__init__.py
pyramid/__check_build/tests/test_check_build.py
pyramid/_build_utils/__init__.py
pyramid/_build_utils/tests/__init__.py
pyramid/arima/__init__.py
pyramid/arima/_arima.cp35-win_amd64.pyd
pyramid/arima/approx.py
pyramid/arima/arima.py
pyramid/arima/auto.py
pyramid/arima/seasonality.py
pyramid/arima/setup.py
pyramid/arima/stationarity.py
pyramid/arima/utils.py
pyramid/arima/warnings.py
pyramid/arima/tests/__init__.py
pyramid/arima/tests/test_approx.py
pyramid/arima/tests/test_arima.py
pyramid/arima/tests/test_c_arima.py
pyramid/arima/tests/test_stationarity.py
pyramid/compat/__init__.py
pyramid/compat/matplotlib.py
pyramid/compat/numpy.py
pyramid/compat/pandas.py
pyramid/compat/python.py
pyramid/compat/statsmodels.py
pyramid/compat/tests/__init__.py
pyramid/compat/tests/test_python.py
pyramid/compat/tests/test_statsmodels.py
pyramid/datasets/__init__.py
pyramid/datasets/heartrate.py
pyramid/datasets/lynx.py
pyramid/datasets/wineind.py
pyramid/datasets/woolyrnq.py
pyramid/datasets/tests/__init__.py
pyramid/datasets/tests/test_load_datasets.py
pyramid/utils/__init__.py
pyramid/utils/array.py
pyramid/utils/metaestimators.py
pyramid/utils/testing.py
pyramid/utils/visualization.py
pyramid/utils/wrapped.py
pyramid/utils/tests/__init__.py
pyramid/utils/tests/test_array.py
pyramid/utils/tests/test_meta.py
pyramid/utils/tests/test_testing.py
pyramid/utils/tests/test_vis.py
pyramid/utils/tests/test_wrapped.py
pyramid_arima-0.9.0.dist-info/AUTHORS.md
pyramid_arima-0.9.0.dist-info/LICENSE
pyramid_arima-0.9.0.dist-info/METADATA
pyramid_arima-0.9.0.dist-info/WHEEL
pyramid_arima-0.9.0.dist-info/top_level.txt
pyramid_arima-0.9.0.dist-info/RECORD
